polyrat/__init__.py
polyrat/aaa.py
polyrat/arnoldi.py
polyrat/basis.py
polyrat/demos.py
polyrat/index.py
polyrat/lagrange.py
polyrat/linratfit.py
polyrat/paaa.py
polyrat/pole_residue.py
polyrat/polynomial.py
polyrat/rational.py
polyrat/rational_ratio.py
polyrat/skiter.py
polyrat/skiter_stabilized.py
polyrat/slp.py
polyrat/sorted_norm.py
polyrat/util.py
polyrat/vecfit.py
polyrat/version.py
polyrat-0.2.2.dist-info/LICENSE
polyrat-0.2.2.dist-info/METADATA
polyrat-0.2.2.dist-info/WHEEL
polyrat-0.2.2.dist-info/top_level.txt
polyrat-0.2.2.dist-info/RECORD
