Metadata-Version: 2.1
Name: polyrat
Version: 0.2.2
Summary: Polynomial and rational function library
Home-page: https://github.com/jeffrey-hokanson/PolyRat
Author: Jeffrey M. Hokanson
Author-email: jeffrey@hokanson.us
License: UNKNOWN
Platform: UNKNOWN
Classifier: Development Status :: 4 - Beta
Classifier: Programming Language :: Python :: 3
Classifier: Programming Language :: Python :: 3.6
Classifier: Programming Language :: Python :: 3.7
Classifier: Programming Language :: Python :: 3.8
Classifier: License :: OSI Approved :: GNU General Public License v3 (GPLv3)
Classifier: Intended Audience :: Science/Research
Classifier: Topic :: Scientific/Engineering :: Mathematics
Requires-Python: >=3.6
